{
  "m_GameObject": {
    "m_FileID": 0,
    "m_PathID": 1575713035151003834
  },
  "m_Enabled": 1,
  "m_Script": {
    "m_FileID": 0,
    "m_PathID": 6078370316984442699
  },
  "m_Name": "",
  "ViewID": 908,
  "formId": -1,
  "walkSpeed": 1.6,
  "runSpeed": 11.0,
  "Origin": {
    "m_FileID": 0,
    "m_PathID": 7783827635245637811
  },
  "Waist": {
    "m_FileID": 0,
    "m_PathID": 7317740548934824311
  },
  "Head": {
    "m_FileID": 0,
    "m_PathID": -8195875963873380927
  },
  "ViewFBX": {
    "m_FileID": 0,
    "m_PathID": 2851576627280974124
  },
  "customCollisionTransforms": [],
  "attentionBonesTransformsIsSet": 1,
  "attentionBonesRotationLimitDegrees": 40.0,
  "attentionBonesPettingLimitDegrees": 15.0,
  "attentionBonesTransforms": [
    {
      "m_FileID": 0,
      "m_PathID": -8195875963873380927
    }
  ],
  "animator": {
    "m_FileID": 0,
    "m_PathID": 2562019400201497816
  },
  "isFlying": 0,
  "haloSocket": {
    "m_FileID": 0,
    "m_PathID": -8935882568722515231
  },
  "faceSocket": {
    "m_FileID": 0,
    "m_PathID": 1411275443487392810
  },
  "bodySocket": {
    "m_FileID": 0,
    "m_PathID": 5015864844327341266
  },
  "groundSocket": {
    "m_FileID": 0,
    "m_PathID": -7782041623584956449
  },
  "centerSocket": {
    "m_FileID": 0,
    "m_PathID": -3613358187429524336
  },
  "feedingSocket": {
    "m_FileID": 0,
    "m_PathID": 3694165086721173487
  },
  "badgeSocket": {
    "m_FileID": 0,
    "m_PathID": -6906941018674503065
  },
  "defaultContext": 0,
  "glowEffect": {
    "m_FileID": 0,
    "m_PathID": 0
  }
}