{
  "m_GameObject": {
    "m_FileID": 0,
    "m_PathID": 6828056488035661644
  },
  "m_Enabled": 1,
  "m_Script": {
    "m_FileID": 0,
    "m_PathID": -3227642854647831317
  },
  "m_Name": "",
  "drivenMaterials": [
    {
      "m_FileID": 0,
      "m_PathID": -3209863880908755103
    },
    {
      "m_FileID": 0,
      "m_PathID": 5915818302683743270
    }
  ],
  "materialPropertyDriver": {
    "xformDatas": [
      {
        "xformDriver": {
          "m_FileID": 0,
          "m_PathID": -2057987537750855299
        },
        "xformDriverAuto": {
          "m_FileID": 0,
          "m_PathID": 0
        },
        "xformDriverCustom": {
          "m_FileID": 0,
          "m_PathID": -2057987537750855299
        },
        "isOverrideDriver": 1,
        "drivenProperty": {
          "m_FileID": 0,
          "m_PathID": -7575198517551511660
        },
        "isOverrideValues": 0,
        "_magnitude": 0.0,
        "_min": 0.0,
        "_max": 0.0,
        "uvColumns": 0,
        "uvRows": 0,
        "uvSets": 0,
        "uvIsStepped": 0,
        "DrivenPropertyIDs": [
          {
            "ID": 636,
            "type": 0,
            "block": 0
          }
        ]
      },
      {
        "xformDriver": {
          "m_FileID": 0,
          "m_PathID": 4439993920575548315
        },
        "xformDriverAuto": {
          "m_FileID": 0,
          "m_PathID": 0
        },
        "xformDriverCustom": {
          "m_FileID": 0,
          "m_PathID": 4439993920575548315
        },
        "isOverrideDriver": 1,
        "drivenProperty": {
          "m_FileID": 1,
          "m_PathID": -8379110596662916849
        },
        "isOverrideValues": 0,
        "_magnitude": 0.0,
        "_min": 0.0,
        "_max": 0.0,
        "uvColumns": 0,
        "uvRows": 0,
        "uvSets": 0,
        "uvIsStepped": 0,
        "DrivenPropertyIDs": [
          {
            "ID": 335,
            "type": 0,
            "block": 0
          }
        ]
      },
      {
        "xformDriver": {
          "m_FileID": 0,
          "m_PathID": 8530998261563408220
        },
        "xformDriverAuto": {
          "m_FileID": 0,
          "m_PathID": 8530998261563408220
        },
        "xformDriverCustom": {
          "m_FileID": 0,
          "m_PathID": 8530998261563408220
        },
        "isOverrideDriver": 1,
        "drivenProperty": {
          "m_FileID": 7,
          "m_PathID": 5738960089038196524
        },
        "isOverrideValues": 1,
        "_magnitude": 0.0,
        "_min": 0.0,
        "_max": 0.0,
        "uvColumns": 0,
        "uvRows": 0,
        "uvSets": 0,
        "uvIsStepped": 0,
        "DrivenPropertyIDs": [
          {
            "ID": 565,
            "type": 1,
            "block": 1
          }
        ]
      },
      {
        "xformDriver": {
          "m_FileID": 0,
          "m_PathID": 8502815737879475547
        },
        "xformDriverAuto": {
          "m_FileID": 0,
          "m_PathID": 0
        },
        "xformDriverCustom": {
          "m_FileID": 0,
          "m_PathID": 8502815737879475547
        },
        "isOverrideDriver": 1,
        "drivenProperty": {
          "m_FileID": 0,
          "m_PathID": 2251799218414720014
        },
        "isOverrideValues": 0,
        "_magnitude": 0.0,
        "_min": 0.0,
        "_max": 0.0,
        "uvColumns": 0,
        "uvRows": 0,
        "uvSets": 0,
        "uvIsStepped": 0,
        "DrivenPropertyIDs": [
          {
            "ID": 552,
            "type": 0,
            "block": 1
          }
        ]
      },
      {
        "xformDriver": {
          "m_FileID": 0,
          "m_PathID": 2042926684729204127
        },
        "xformDriverAuto": {
          "m_FileID": 0,
          "m_PathID": 0
        },
        "xformDriverCustom": {
          "m_FileID": 0,
          "m_PathID": 2042926684729204127
        },
        "isOverrideDriver": 1,
        "drivenProperty": {
          "m_FileID": 6,
          "m_PathID": 5160718438927878732
        },
        "isOverrideValues": 0,
        "_magnitude": 0.0,
        "_min": 0.0,
        "_max": 0.0,
        "uvColumns": 0,
        "uvRows": 0,
        "uvSets": 0,
        "uvIsStepped": 0,
        "DrivenPropertyIDs": [
          {
            "ID": 553,
            "type": 0,
            "block": 1
          }
        ]
      }
    ],
    "xformCache": [
      {
        "xformDriver": {
          "m_FileID": 0,
          "m_PathID": -2057987537750855299
        },
        "xformDataIndices": [
          0
        ],
        "xformDataIndexList": [
          0
        ]
      },
      {
        "xformDriver": {
          "m_FileID": 0,
          "m_PathID": 4439993920575548315
        },
        "xformDataIndices": [
          1
        ],
        "xformDataIndexList": [
          1
        ]
      },
      {
        "xformDriver": {
          "m_FileID": 0,
          "m_PathID": 8530998261563408220
        },
        "xformDataIndices": [
          2
        ],
        "xformDataIndexList": [
          2
        ]
      },
      {
        "xformDriver": {
          "m_FileID": 0,
          "m_PathID": 8502815737879475547
        },
        "xformDataIndices": [
          3
        ],
        "xformDataIndexList": [
          3
        ]
      },
      {
        "xformDriver": {
          "m_FileID": 0,
          "m_PathID": 2042926684729204127
        },
        "xformDataIndices": [
          4
        ],
        "xformDataIndexList": [
          4
        ]
      }
    ],
    "drivenMeshRenderers": [
      {
        "Default": {
          "m_FileID": 0,
          "m_PathID": -5437087626749250833
        },
        "Custom": {
          "m_FileID": 0,
          "m_PathID": 0
        },
        "isOverride": 0
      },
      {
        "Default": {
          "m_FileID": 0,
          "m_PathID": -2195892636627197129
        },
        "Custom": {
          "m_FileID": 0,
          "m_PathID": 0
        },
        "isOverride": 0
      }
    ],
    "cachedRenderers": [
      {
        "m_FileID": 0,
        "m_PathID": -5437087626749250833
      },
      {
        "m_FileID": 0,
        "m_PathID": -2195892636627197129
      }
    ],
    "uvFaceA": {
      "isActive": 0,
      "uvStep": {
        "x": "NaN",
        "y": "NaN"
      }
    },
    "uvFaceB": {
      "isActive": 1,
      "uvStep": {
        "x": 0.5,
        "y": 0.25
      }
    },
    "uvDirectA": {
      "isActive": 0,
      "uvStep": {
        "x": "NaN",
        "y": "NaN"
      }
    },
    "uvDirectB": {
      "isActive": 0,
      "uvStep": {
        "x": "NaN",
        "y": "NaN"
      }
    },
    "originalFaceJointY": 0.0,
    "angryFaceJointY": 4.0,
    "smileFaceJointY": 0.0,
    "extraFaceJointOverride": []
  }
}